{
  "name": "ะงะตะปะพะฒะตัะตัะบะพะต ะฟะพะทะฝะฐะฝะธะต ะะณะพ ััะตัะฐ ะธ ะณัะฐะฝะธัั (ะะฐััะตะป ะะตัััะฐะฝ).pdf",
  "path": "001 ๐ชฒ Philosophy/1 ๐ Bright Personalities/1872 ๐งฎ Rassel Bertran_/ะงะตะปะพะฒะตัะตัะบะพะต ะฟะพะทะฝะฐะฝะธะต ะะณะพ ััะตัะฐ ะธ ะณัะฐะฝะธัั (ะะฐััะตะป ะะตัััะฐะฝ).pdf",
  "type": "file",
  "id": "chelovec-b2d4a620",
  "nickname": "001๐ชฒPhilos๐น1๐BrightPe๐น1872๐งฎRasse๐นะงะตะปะพะฒะตัะตัะบ๐นb2d4a620",
  "home": "../data/data-librarium/1 ๐ Librarium Privatus",
  "parent": "1872-ras-db19f42e",
  "title": "ะงะตะปะพะฒะตัะตัะบะพะต ะฟะพะทะฝะฐะฝะธะต ะะณะพ ััะตัะฐ ะธ ะณัะฐะฝะธัั (ะะฐััะตะป ะะตัััะฐะฝ).pdf",
  "cover": "chelovec-b2d4a620.jpg",
  "cover_ratio": 1.538
}