{
  "name": "ะะตััะตะฝ ะ.ะ. - ะกะพัะธะฝะตะฝะธั ะฒ 2-ั ัะพะผะฐั ั.2 (ะคะธะปะพัะพััะบะพะต ะฝะฐัะปะตะดะธะต ั.96) - 1986.pdf",
  "path": "001 ๐ชฒ Philosophy/1 ๐ Bright Personalities/ะะตััะตะฝ/ะะตััะตะฝ ะ.ะ. - ะกะพัะธะฝะตะฝะธั ะฒ 2-ั ัะพะผะฐั ั.2 (ะคะธะปะพัะพััะบะพะต ะฝะฐัะปะตะดะธะต ั.96) - 1986.pdf",
  "type": "file",
  "id": "gertsen--504501a1",
  "nickname": "001๐ชฒPhilos๐น1๐BrightPe๐นะะตััะตะฝ๐นะะตััะตะฝะ.ะ.๐น504501a1",
  "home": "../data/data-librarium/1 ๐ Librarium Privatus",
  "parent": "gertsen-54387bf2",
  "title": "ะะตััะตะฝ ะ.ะ. - ะกะพัะธะฝะตะฝะธั ะฒ 2-ั ัะพะผะฐั ั.2 (ะคะธะปะพัะพััะบะพะต ะฝะฐัะปะตะดะธะต ั.96) - 1986.pdf",
  "cover": "gertsen--504501a1.jpg",
  "cover_ratio": 1.487
}