{
  "name": "Коплстон Ф. - История философии.Древняя Греция и Древний Рим.Том I-2003.fb2",
  "path": "001 🪲 Philosophy/1 🏂 Bright Personalities/1907 - Copleston Frederick_/Коплстон Ф. - История философии.Древняя Греция и Древний Рим.В 2 томах-2003/Коплстон Ф. - История философии.Древняя Греция и Древний Рим.Том I-2003/Коплстон Ф. - История философии.Древняя Греция и Древний Рим.Том I-2003.fb2",
  "type": "file",
  "id": "koplston-ad2f8abb",
  "nickname": "001🪲Philos🔹1🏂BrightPe🔹1907-Cople🔹КоплстонФ.🔹КоплстонФ.🔹КоплстонФ.🔹ad2f8abb",
  "home": "../data/data-librarium/1 🏛 Librarium Privatus",
  "parent": "koplston-2d2a941a",
  "title": "Коплстон Ф. - История философии.Древняя Греция и Древний Рим.Том I-2003.fb2"
}