{
  "name": "ะัะพััะตะธฬัะธะต ะฟัะธะผะตัั ะผะฐัะตะผะฐัะธัะตัะบะธั ะดะพะบะฐะทะฐัะตะปัััะฒ (ะฃัะฟะตะฝัะบะธะธฬ ะ.ะ.).pdf",
  "path": "002 ๐ Mathimatics/74 - Popular. Mathimatics/ะัะพััะตะธฬัะธะต ะฟัะธะผะตัั ะผะฐัะตะผะฐัะธัะตัะบะธั ะดะพะบะฐะทะฐัะตะปัััะฒ (ะฃัะฟะตะฝัะบะธะธฬ ะ.ะ.).pdf",
  "type": "file",
  "id": "prosteis-5797c99a",
  "nickname": "002๐Mathim๐น74-Popular๐นะัะพััะตะธฬัะธ๐น5797c99a",
  "home": "../data/data-librarium/1 ๐ Librarium Privatus",
  "parent": "74-popul-ed16db23",
  "title": "ะัะพััะตะธฬัะธะต ะฟัะธะผะตัั ะผะฐัะตะผะฐัะธัะตัะบะธั ะดะพะบะฐะทะฐัะตะปัััะฒ (ะฃัะฟะตะฝัะบะธะธฬ ะ.ะ.).pdf",
  "cover": "prosteis-5797c99a.jpg",
  "cover_ratio": 0.707
}