{
  "name": "Программист-прагматик 2-е юбилейное издание (Эндрю Хант Дэвид Томас).pdf",
  "path": "003 🪁 Computer Science/304 - Down IT - 29 dec/Программист-прагматик 2-е юбилейное издание (Эндрю Хант Дэвид Томас).pdf",
  "type": "file",
  "id": "programm-513a2bfb",
  "nickname": "003🪁Comput🔹304-DownIT🔹Программис🔹513a2bfb",
  "home": "../data/data-librarium/1 🏛 Librarium Privatus",
  "parent": "304-down-b421c5e6",
  "title": "Программист-прагматик 2-е юбилейное издание (Эндрю Хант Дэвид Томас).pdf"
}