{
  "name": "Маленькая книга о большой теории струн в поисках принципов устройства Вселенной (Стивен Габсер пер. с англ. А. Пасечник.pdf",
  "path": "004 🌈 Physics/phys-22/Маленькая книга о большой теории струн в поисках принципов устройства Вселенной (Стивен Габсер пер. с англ. А. Пасечник.pdf",
  "type": "file",
  "id": "malenkai-fb65823a",
  "nickname": "004🌈Physic🔹phys-22🔹Маленькаяк🔹fb65823a",
  "home": "../data/data-librarium/1 🏛 Librarium Privatus",
  "parent": "phys-22-0b1dbb40",
  "title": "Маленькая книга о большой теории струн в поисках принципов устройства Вселенной (Стивен Габсер пер. с англ. А. Пасечник.pdf",
  "cover": "malenkai-fb65823a.jpg",
  "cover_ratio": 1.414
}