{
  "name": "Три склянки пополудни и другие задачи по лингвистике (Бердичевский А. Пиперски А.).pdf",
  "path": "014 🍒 Linguistics/Три склянки пополудни и другие задачи по лингвистике (Бердичевский А. Пиперски А.).pdf",
  "type": "file",
  "id": "tri-skli-e5b92a8b",
  "nickname": "014🍒Lingui🔹Трисклянки🔹e5b92a8b",
  "home": "../data/data-librarium/1 🏛 Librarium Privatus",
  "parent": "014-ling-d90a22c0",
  "title": "Три склянки пополудни и другие задачи по лингвистике (Бердичевский А. Пиперски А.).pdf",
  "cover": "tri-skli-e5b92a8b.jpg",
  "cover_ratio": 1.506
}