{
  "name": "Лучшее в нас. Почему насилия в мире стало меньше (Стивен Пинкер).epub",
  "path": "015 🎩 Cognitive science/Лучшее в нас. Почему насилия в мире стало меньше (Стивен Пинкер).epub",
  "type": "file",
  "id": "luchshee-61e952a4",
  "nickname": "015🎩Cognit🔹Лучшеевнас🔹61e952a4",
  "home": "../data/data-librarium/1 🏛 Librarium Privatus",
  "parent": "015-cogn-f0aa6096",
  "title": "Лучшее в нас. Почему насилия в мире стало меньше (Стивен Пинкер).epub"
}