{
  "name": "Внедрение искусственного интеллекта в бизнес-практику Преимущества и сложности bookinier (Томас Дэвенпорт).epub",
  "path": "019 🐠 AI Predictions/Внедрение искусственного интеллекта в бизнес-практику Преимущества и сложности bookinier (Томас Дэвенпорт).epub",
  "type": "file",
  "id": "vnedreni-e2ce14a4",
  "nickname": "019🐠AIPred🔹Внедрениеи🔹e2ce14a4",
  "home": "../data/data-librarium/1 🏛 Librarium Privatus",
  "parent": "019-ai-p-2e6597e0",
  "title": "Внедрение искусственного интеллекта в бизнес-практику Преимущества и сложности bookinier (Томас Дэвенпорт).epub",
  "cover": "vnedreni-e2ce14a4.jpg",
  "cover_ratio": 1.471
}