{
  "name": "Приключения математика Улам С.djvu",
  "path": "706 - R&C Pub/Приключения математика Улам С.djvu",
  "type": "file",
  "id": "prikliuc-7339877c",
  "nickname": "706-R&CPub🔹Приключени🔹7339877c",
  "home": "../data/data-librarium/1 🏛 Librarium Privatus",
  "parent": "706-r-c--85ae7372",
  "title": "Приключения математика Улам С.djvu",
  "cover": "prikliuc-7339877c.jpg",
  "cover_ratio": 1.414
}