{
  "name": "Идеология и наука дискуссии советски.pdf",
  "path": "998 🥞 Books-Download/books-23-05may-27/Идеология и наука дискуссии советски.pdf",
  "type": "file",
  "id": "ideologi-d394cb2b",
  "nickname": "998🥞Books-🔹books-23-0🔹Идеологияи🔹d394cb2b",
  "home": "../data/data-librarium/1 🏛 Librarium Privatus",
  "parent": "books-23-65e58c20",
  "title": "Идеология и наука дискуссии советски.pdf",
  "cover": "ideologi-d394cb2b.jpg",
  "cover_ratio": 1.414
}