{
  "name": "Черная книга Эренбург Илья Григорьев.pdf",
  "path": "998 🥞 Books-Download/books-23-05may-27/Черная книга Эренбург Илья Григорьев.pdf",
  "type": "file",
  "id": "chernaia-5467c35b",
  "nickname": "998🥞Books-🔹books-23-0🔹Чернаякниг🔹5467c35b",
  "home": "../data/data-librarium/1 🏛 Librarium Privatus",
  "parent": "books-23-65e58c20",
  "title": "Черная книга Эренбург Илья Григорьев.pdf",
  "cover": "chernaia-5467c35b.jpg",
  "cover_ratio": 1.415
}