{
  "name": "Ранняя философия Эдмунда Гуссерля Га.pdf",
  "path": "998 🥞 Books-Download/books-23-05may-27/Ранняя философия Эдмунда Гуссерля Га.pdf",
  "type": "file",
  "id": "ranniaia-a6fc426d",
  "nickname": "998🥞Books-🔹books-23-0🔹Ранняяфило🔹a6fc426d",
  "home": "../data/data-librarium/1 🏛 Librarium Privatus",
  "parent": "books-23-65e58c20",
  "title": "Ранняя философия Эдмунда Гуссерля Га.pdf",
  "cover": "ranniaia-a6fc426d.jpg",
  "cover_ratio": 0.668
}