{
  "name": "Философия науки С А Лебедев А Н Авд.djvu.pdf",
  "path": "998 🥞 Books-Download/books-23-03mar-05/Философия науки С А Лебедев А Н Авд.djvu.pdf",
  "type": "file",
  "id": "filosofi-69a9f53e",
  "nickname": "998🥞Books-🔹books-23-0🔹Философиян🔹69a9f53e",
  "home": "../data/data-librarium/1 🏛 Librarium Privatus",
  "parent": "books-23-d7dc8062",
  "title": "Философия науки С А Лебедев А Н Авд.djvu.pdf",
  "cover": "filosofi-69a9f53e.jpg",
  "cover_ratio": 1.491
}